{
	"configurations" : 
	[
		{
			"directories" : 
			[
				{
					"build" : ".",
					"jsonFile" : "directory-.-Debug-f5ebdc15457944623624.json",
					"minimumCMakeVersion" : 
					{
						"string" : "3.29"
					},
					"projectIndex" : 0,
					"source" : ".",
					"targetIndexes" : 
					[
						0
					]
				}
			],
			"name" : "Debug",
			"projects" : 
			[
				{
					"directoryIndexes" : 
					[
						0
					],
					"name" : "Puissance_C",
					"targetIndexes" : 
					[
						0
					]
				}
			],
			"targets" : 
			[
				{
					"directoryIndex" : 0,
					"id" : "Puissance_C::@6890427a1f51a3e7e1df",
					"jsonFile" : "target-Puissance_C-Debug-9754e99eb9d96aa041df.json",
					"name" : "Puissance_C",
					"projectIndex" : 0
				}
			]
		}
	],
	"kind" : "codemodel",
	"paths" : 
	{
		"build" : "/Users/enzoborges/Desktop/ESGI/3AL/Puissance-C/cmake-build-debug",
		"source" : "/Users/enzoborges/Desktop/ESGI/3AL/Puissance-C"
	},
	"version" : 
	{
		"major" : 2,
		"minor" : 7
	}
}
